paper_data/__init__.py
paper_data/config_parser.py
paper_data/manager.py
paper_data/run_pipeline.py
paper_data/ingestion/__init__.py
paper_data/ingestion/base.py
paper_data/ingestion/google_drive.py
paper_data/ingestion/http.py
paper_data/ingestion/huggingface_ds.py
paper_data/ingestion/local.py
paper_data/ingestion/wrds_conn.py
paper_data/wrangling/__init__.py
paper_data/wrangling/augmenter.py
paper_data/wrangling/cleaner.py
paper_data-0.1.2.dist-info/METADATA
paper_data-0.1.2.dist-info/WHEEL
paper_data-0.1.2.dist-info/entry_points.txt
paper_data-0.1.2.dist-info/licenses/LICENSE
paper_data-0.1.2.dist-info/RECORD
