Metadata-Version: 2.4
Name: paper-data
Version: 0.1.2
Summary: A flexible, configuration-driven data pipeline for asset-pricing research.
Author-email: Lorenzo Varese <55581163+lorenzovarese@users.noreply.github.com>
License-File: LICENSE
Requires-Python: >=3.11
Requires-Dist: datasets>=3.6.0
Requires-Dist: pandas>=2.2.3
Requires-Dist: polars>=1.30.0
Requires-Dist: pyarrow>=20.0.0
Requires-Dist: pydantic>=2.11.5
Requires-Dist: pyyaml>=6.0.2
Requires-Dist: requests>=2.32.3
Requires-Dist: tqdm>=4.67.1
Requires-Dist: wrds>=3.3.0
